alea_preprocess-0.1.12.dist-info/METADATA
alea_preprocess-0.1.12.dist-info/WHEEL
alea_preprocess.libs/libssl-fa9d51fe.so.3
alea_preprocess.libs/libcrypto-8173d9ca.so.3
alea_preprocess/parsers/html/__init__.py
alea_preprocess/parsers/html/conversion.pyi
alea_preprocess/parsers/__init__.py
alea_preprocess/parsers/pdf/conversion.pyi
alea_preprocess/parsers/pdf/detection.pyi
alea_preprocess/parsers/pdf/__init__.py
alea_preprocess/parsers/tika/__init__.py
alea_preprocess/parsers/tika/client.pyi
alea_preprocess/io/__init__.py
alea_preprocess/io/fs/files.pyi
alea_preprocess/io/fs/directories.pyi
alea_preprocess/io/fs/file_info.pyi
alea_preprocess/io/fs/__init__.py
alea_preprocess/__init__.py
alea_preprocess/algos/unicode/normalizations.pyi
alea_preprocess/algos/unicode/categories.pyi
alea_preprocess/algos/unicode/segmentations.pyi
alea_preprocess/algos/unicode/__init__.py
alea_preprocess/algos/uu/__init__.pyi
alea_preprocess/algos/tokenizers.pyi
alea_preprocess/algos/ngrams/chars.pyi
alea_preprocess/algos/ngrams/categories.pyi
alea_preprocess/algos/ngrams/__init__.py
alea_preprocess/algos/ngrams/binary.pyi
alea_preprocess/algos/ngrams/words.pyi
alea_preprocess/algos/hashing/blake3.pyi
alea_preprocess/algos/hashing/blake2.pyi
alea_preprocess/algos/hashing/rolling.pyi
alea_preprocess/algos/hashing/__init__.py
alea_preprocess/algos/hashing/ctph.pyi
alea_preprocess/algos/__init__.py
alea_preprocess/algos/similarity/strings.pyi
alea_preprocess/algos/similarity/__init__.py
alea_preprocess/algos/splitting/simple.pyi
alea_preprocess/algos/splitting/__init__.py
alea_preprocess/alea_preprocess.cpython-312-x86_64-linux-gnu.so
alea_preprocess-0.1.12.dist-info/RECORD
