Metadata-Version: 2.3
Name: alea-preprocess
Version: 0.1.12
Classifier: Programming Language :: Rust
Classifier: Programming Language :: Python :: Implementation :: CPython
Classifier: Programming Language :: Python :: Implementation :: PyPy
Classifier: Development Status :: 3 - Alpha
Classifier: Intended Audience :: Science/Research
Classifier: Intended Audience :: Developers
Classifier: License :: OSI Approved :: MIT License
Classifier: Operating System :: OS Independent
Classifier: Programming Language :: Python
Classifier: Programming Language :: Python :: 3
Classifier: Programming Language :: Python :: 3.10
Classifier: Programming Language :: Python :: 3.11
Classifier: Programming Language :: Python :: 3.12
Classifier: Programming Language :: Python :: 3.13
Classifier: Topic :: Software Development :: Libraries :: Python Modules
Classifier: Topic :: Scientific/Engineering :: Information Analysis
Classifier: Topic :: Scientific/Engineering :: Artificial Intelligence
Classifier: Topic :: Utilities
Summary: Efficient, accessible preprocessing routines for pretrain, SFT, and DPO training data preparation from the ALEA Institute.
Keywords: alea,llm,data,preprocess,pretrain,kl3m
Home-Page: https://aleainstitute.ai/
Author: ALEA Institute <hello@aleainstitute.ai>
Author-email: ALEA Institute <hello@aleainstitute.ai>
License: MIT
Requires-Python: >=3.10, <4.0
Project-URL: Source Code, https://github.com/alea-institute/alea-preprocess
